{
    "rooms": [
        {
            "name": "livingroom",
            "transName": "livingroom",
            "locations": [
                {
                    "start": "2013-11-16 09:22:14",
                    "end": "2013-11-16 09:23:07"
                },
                {
                    "start": "2013-11-16 09:28:18",
                    "end": "2013-11-16 09:30:59"
                },
                {
                    "start": "2013-11-16 09:31:48",
                    "end": "2013-11-16 09:39:02"
                },
                {
                    "start": "2013-11-16 09:40:14",
                    "end": "2013-11-16 09:55:52"
                },
                {
                    "start": "2013-11-16 09:59:14",
                    "end": "2013-11-16 09:59:55"
                },
                {
                    "start": "2013-11-16 10:00:43",
                    "end": "2013-11-16 10:01:06"
                },
                {
                    "start": "2013-11-16 10:16:45",
                    "end": "2013-11-16 10:16:52"
                },
                {
                    "start": "2013-11-16 10:16:55",
                    "end": "2013-11-16 10:17:10"
                },
                {
                    "start": "2013-11-16 10:19:10",
                    "end": "2013-11-16 10:19:17"
                },
                {
                    "start": "2013-11-16 10:19:28",
                    "end": "2013-11-16 10:20:25"
                },
                {
                    "start": "2013-11-16 10:21:49",
                    "end": "2013-11-16 10:22:06"
                },
                {
                    "start": "2013-11-16 10:24:02",
                    "end": "2013-11-16 10:28:15"
                },
                {
                    "start": "2013-11-16 10:29:08",
                    "end": "2013-11-16 10:33:26"
                },
                {
                    "start": "2013-11-16 10:35:56",
                    "end": "2013-11-16 10:36:02"
                },
                {
                    "start": "2013-11-16 10:36:06",
                    "end": "2013-11-16 10:55:41"
                },
                {
                    "start": "2013-11-16 10:57:00",
                    "end": "2013-11-16 11:05:18"
                },
                {
                    "start": "2013-11-16 11:05:21",
                    "end": "2013-11-16 11:35:37"
                },
                {
                    "start": "2013-11-16 11:39:18",
                    "end": "2013-11-16 11:39:48"
                },
                {
                    "start": "2013-11-16 11:39:52",
                    "end": "2013-11-16 11:41:40"
                },
                {
                    "start": "2013-11-16 11:41:43",
                    "end": "2013-11-16 11:41:49"
                },
                {
                    "start": "2013-11-16 15:38:07",
                    "end": "2013-11-16 15:39:37"
                },
                {
                    "start": "2013-11-16 15:39:44",
                    "end": "2013-11-16 15:39:52"
                },
                {
                    "start": "2013-11-16 15:39:55",
                    "end": "2013-11-16 15:40:05"
                },
                {
                    "start": "2013-11-16 15:41:04",
                    "end": "2013-11-16 15:41:14"
                },
                {
                    "start": "2013-11-16 15:49:14",
                    "end": "2013-11-16 15:49:25"
                },
                {
                    "start": "2013-11-16 15:49:42",
                    "end": "2013-11-16 15:51:24"
                },
                {
                    "start": "2013-11-16 15:57:49",
                    "end": "2013-11-16 15:58:27"
                },
                {
                    "start": "2013-11-16 16:00:17",
                    "end": "2013-11-16 16:00:47"
                },
                {
                    "start": "2013-11-16 16:01:45",
                    "end": "2013-11-16 16:03:28"
                },
                {
                    "start": "2013-11-16 16:03:40",
                    "end": "2013-11-16 16:04:16"
                },
                {
                    "start": "2013-11-16 16:07:15",
                    "end": "2013-11-16 16:07:42"
                },
                {
                    "start": "2013-11-16 16:18:32",
                    "end": "2013-11-16 16:21:01"
                },
                {
                    "start": "2013-11-16 16:21:12",
                    "end": "2013-11-16 16:39:55"
                },
                {
                    "start": "2013-11-16 16:41:17",
                    "end": "2013-11-16 16:51:18"
                },
                {
                    "start": "2013-11-16 16:51:27",
                    "end": "2013-11-16 16:54:01"
                },
                {
                    "start": "2013-11-16 16:56:38",
                    "end": "2013-11-16 16:56:58"
                },
                {
                    "start": "2013-11-16 16:57:44",
                    "end": "2013-11-16 16:58:38"
                },
                {
                    "start": "2013-11-16 16:59:16",
                    "end": "2013-11-16 17:00:03"
                },
                {
                    "start": "2013-11-16 17:01:00",
                    "end": "2013-11-16 17:02:10"
                },
                {
                    "start": "2013-11-16 17:04:16",
                    "end": "2013-11-16 17:06:23"
                },
                {
                    "start": "2013-11-16 17:07:11",
                    "end": "2013-11-16 17:11:48"
                },
                {
                    "start": "2013-11-16 17:15:05",
                    "end": "2013-11-16 17:34:08"
                },
                {
                    "start": "2013-11-16 17:39:42",
                    "end": "2013-11-16 17:41:52"
                },
                {
                    "start": "2013-11-16 17:43:17",
                    "end": "2013-11-16 17:43:43"
                },
                {
                    "start": "2013-11-16 17:44:45",
                    "end": "2013-11-16 17:47:12"
                },
                {
                    "start": "2013-11-16 17:48:15",
                    "end": "2013-11-16 17:48:39"
                },
                {
                    "start": "2013-11-16 17:49:06",
                    "end": "2013-11-16 17:49:43"
                },
                {
                    "start": "2013-11-16 17:49:47",
                    "end": "2013-11-16 17:55:28"
                },
                {
                    "start": "2013-11-16 17:55:32",
                    "end": "2013-11-16 18:25:20"
                },
                {
                    "start": "2013-11-16 18:25:51",
                    "end": "2013-11-16 18:27:58"
                },
                {
                    "start": "2013-11-16 18:32:16",
                    "end": "2013-11-16 18:34:17"
                },
                {
                    "start": "2013-11-16 18:34:46",
                    "end": "2013-11-16 18:35:09"
                },
                {
                    "start": "2013-11-16 18:39:39",
                    "end": "2013-11-16 18:42:04"
                },
                {
                    "start": "2013-11-16 18:43:21",
                    "end": "2013-11-16 18:45:19"
                },
                {
                    "start": "2013-11-16 18:45:25",
                    "end": "2013-11-16 18:51:27"
                },
                {
                    "start": "2013-11-16 18:51:59",
                    "end": "2013-11-16 18:52:39"
                },
                {
                    "start": "2013-11-16 18:54:46",
                    "end": "2013-11-16 19:28:33"
                },
                {
                    "start": "2013-11-16 19:28:49",
                    "end": "2013-11-16 19:28:58"
                },
                {
                    "start": "2013-11-16 19:29:49",
                    "end": "2013-11-16 19:30:09"
                },
                {
                    "start": "2013-11-16 19:30:25",
                    "end": "2013-11-16 19:30:40"
                },
                {
                    "start": "2013-11-16 19:31:33",
                    "end": "2013-11-16 19:31:47"
                },
                {
                    "start": "2013-11-16 19:36:33",
                    "end": "2013-11-16 19:36:37"
                },
                {
                    "start": "2013-11-16 19:36:48",
                    "end": "2013-11-16 19:38:08"
                },
                {
                    "start": "2013-11-16 19:41:17",
                    "end": "2013-11-16 19:41:25"
                },
                {
                    "start": "2013-11-16 19:42:01",
                    "end": "2013-11-16 19:44:17"
                },
                {
                    "start": "2013-11-16 19:44:52",
                    "end": "2013-11-16 19:46:37"
                },
                {
                    "start": "2013-11-16 19:46:42",
                    "end": "2013-11-16 19:53:22"
                },
                {
                    "start": "2013-11-16 19:55:54",
                    "end": "2013-11-16 20:12:57"
                },
                {
                    "start": "2013-11-16 20:13:17",
                    "end": "2013-11-16 20:33:20"
                },
                {
                    "start": "2013-11-16 20:33:34",
                    "end": "2013-11-16 20:33:38"
                },
                {
                    "start": "2013-11-16 20:33:41",
                    "end": "2013-11-16 20:33:45"
                },
                {
                    "start": "2013-11-16 20:34:56",
                    "end": "2013-11-16 20:35:06"
                },
                {
                    "start": "2013-11-16 20:35:10",
                    "end": "2013-11-16 20:35:14"
                },
                {
                    "start": "2013-11-16 20:39:20",
                    "end": "2013-11-16 20:39:55"
                },
                {
                    "start": "2013-11-16 20:40:46",
                    "end": "2013-11-16 20:40:53"
                },
                {
                    "start": "2013-11-16 20:40:57",
                    "end": "2013-11-16 20:44:49"
                },
                {
                    "start": "2013-11-16 20:50:23",
                    "end": "2013-11-16 20:51:11"
                },
                {
                    "start": "2013-11-16 20:51:49",
                    "end": "2013-11-16 20:52:04"
                },
                {
                    "start": "2013-11-16 21:17:56",
                    "end": "2013-11-16 21:18:41"
                },
                {
                    "start": "2013-11-16 21:19:22",
                    "end": "2013-11-16 21:20:42"
                },
                {
                    "start": "2013-11-16 21:22:12",
                    "end": "2013-11-16 21:23:58"
                },
                {
                    "start": "2013-11-16 21:29:25",
                    "end": "2013-11-16 21:50:07"
                },
                {
                    "start": "2013-11-16 21:50:55",
                    "end": "2013-11-16 21:51:32"
                },
                {
                    "start": "2013-11-16 21:51:35",
                    "end": "2013-11-16 21:52:46"
                }
            ]
        },
        {
            "name": "bathroom",
            "transName": "bathroom",
            "locations": [
                {
                    "start": "2013-11-16 08:19:22",
                    "end": "2013-11-16 08:25:43"
                },
                {
                    "start": "2013-11-16 09:16:55",
                    "end": "2013-11-16 09:22:14"
                },
                {
                    "start": "2013-11-16 22:36:01",
                    "end": "2013-11-16 23:03:31"
                },
                {
                    "start": "2013-11-16 23:03:57",
                    "end": "2013-11-16 23:05:55"
                }
            ]
        },
        {
            "name": "toilet",
            "transName": "toilet",
            "locations": [
                {
                    "start": "2013-11-16 02:14:14",
                    "end": "2013-11-16 02:17:46"
                },
                {
                    "start": "2013-11-16 10:01:06",
                    "end": "2013-11-16 10:16:38"
                },
                {
                    "start": "2013-11-16 10:33:26",
                    "end": "2013-11-16 10:35:56"
                },
                {
                    "start": "2013-11-16 11:35:37",
                    "end": "2013-11-16 11:39:15"
                },
                {
                    "start": "2013-11-16 15:40:05",
                    "end": "2013-11-16 15:40:37"
                },
                {
                    "start": "2013-11-16 15:40:41",
                    "end": "2013-11-16 15:41:00"
                },
                {
                    "start": "2013-11-16 15:44:07",
                    "end": "2013-11-16 15:47:08"
                },
                {
                    "start": "2013-11-16 18:35:09",
                    "end": "2013-11-16 18:39:39"
                },
                {
                    "start": "2013-11-16 19:29:06",
                    "end": "2013-11-16 19:29:13"
                },
                {
                    "start": "2013-11-16 19:29:22",
                    "end": "2013-11-16 19:29:49"
                },
                {
                    "start": "2013-11-16 20:33:20",
                    "end": "2013-11-16 20:33:34"
                },
                {
                    "start": "2013-11-16 20:33:38",
                    "end": "2013-11-16 20:33:41"
                },
                {
                    "start": "2013-11-16 20:33:45",
                    "end": "2013-11-16 20:33:49"
                },
                {
                    "start": "2013-11-16 20:33:57",
                    "end": "2013-11-16 20:34:08"
                },
                {
                    "start": "2013-11-16 20:34:17",
                    "end": "2013-11-16 20:34:53"
                },
                {
                    "start": "2013-11-16 20:35:06",
                    "end": "2013-11-16 20:35:10"
                },
                {
                    "start": "2013-11-16 20:35:14",
                    "end": "2013-11-16 20:39:17"
                },
                {
                    "start": "2013-11-16 21:24:28",
                    "end": "2013-11-16 21:29:08"
                },
                {
                    "start": "2013-11-16 21:52:49",
                    "end": "2013-11-16 21:56:23"
                }
            ]
        },
        {
            "name": "kitchen",
            "transName": "kitchen",
            "locations": [
                {
                    "start": "2013-11-16 09:23:07",
                    "end": "2013-11-16 09:28:18"
                },
                {
                    "start": "2013-11-16 09:30:59",
                    "end": "2013-11-16 09:31:48"
                },
                {
                    "start": "2013-11-16 09:39:02",
                    "end": "2013-11-16 09:40:14"
                },
                {
                    "start": "2013-11-16 09:55:52",
                    "end": "2013-11-16 09:59:14"
                },
                {
                    "start": "2013-11-16 09:59:55",
                    "end": "2013-11-16 10:00:43"
                },
                {
                    "start": "2013-11-16 10:16:38",
                    "end": "2013-11-16 10:16:45"
                },
                {
                    "start": "2013-11-16 10:17:10",
                    "end": "2013-11-16 10:19:10"
                },
                {
                    "start": "2013-11-16 10:19:17",
                    "end": "2013-11-16 10:19:28"
                },
                {
                    "start": "2013-11-16 10:20:25",
                    "end": "2013-11-16 10:21:49"
                },
                {
                    "start": "2013-11-16 10:22:06",
                    "end": "2013-11-16 10:24:02"
                },
                {
                    "start": "2013-11-16 10:28:15",
                    "end": "2013-11-16 10:29:08"
                },
                {
                    "start": "2013-11-16 10:36:02",
                    "end": "2013-11-16 10:36:06"
                },
                {
                    "start": "2013-11-16 10:55:41",
                    "end": "2013-11-16 10:57:00"
                },
                {
                    "start": "2013-11-16 11:05:18",
                    "end": "2013-11-16 11:05:21"
                },
                {
                    "start": "2013-11-16 11:39:15",
                    "end": "2013-11-16 11:39:18"
                },
                {
                    "start": "2013-11-16 11:39:48",
                    "end": "2013-11-16 11:39:52"
                },
                {
                    "start": "2013-11-16 11:41:40",
                    "end": "2013-11-16 11:41:43"
                },
                {
                    "start": "2013-11-16 11:41:49",
                    "end": "2013-11-16 11:42:03"
                },
                {
                    "start": "2013-11-16 15:39:37",
                    "end": "2013-11-16 15:39:44"
                },
                {
                    "start": "2013-11-16 15:40:37",
                    "end": "2013-11-16 15:40:41"
                },
                {
                    "start": "2013-11-16 15:41:00",
                    "end": "2013-11-16 15:41:04"
                },
                {
                    "start": "2013-11-16 15:42:37",
                    "end": "2013-11-16 15:44:07"
                },
                {
                    "start": "2013-11-16 15:47:08",
                    "end": "2013-11-16 15:49:14"
                },
                {
                    "start": "2013-11-16 15:49:25",
                    "end": "2013-11-16 15:49:42"
                },
                {
                    "start": "2013-11-16 15:51:24",
                    "end": "2013-11-16 15:57:49"
                },
                {
                    "start": "2013-11-16 15:58:27",
                    "end": "2013-11-16 16:00:17"
                },
                {
                    "start": "2013-11-16 16:00:47",
                    "end": "2013-11-16 16:01:45"
                },
                {
                    "start": "2013-11-16 16:03:28",
                    "end": "2013-11-16 16:03:40"
                },
                {
                    "start": "2013-11-16 16:04:16",
                    "end": "2013-11-16 16:07:15"
                },
                {
                    "start": "2013-11-16 16:07:42",
                    "end": "2013-11-16 16:18:32"
                },
                {
                    "start": "2013-11-16 16:21:01",
                    "end": "2013-11-16 16:21:12"
                },
                {
                    "start": "2013-11-16 16:39:55",
                    "end": "2013-11-16 16:41:17"
                },
                {
                    "start": "2013-11-16 16:51:18",
                    "end": "2013-11-16 16:51:27"
                },
                {
                    "start": "2013-11-16 16:54:01",
                    "end": "2013-11-16 16:56:38"
                },
                {
                    "start": "2013-11-16 16:56:58",
                    "end": "2013-11-16 16:57:44"
                },
                {
                    "start": "2013-11-16 16:58:38",
                    "end": "2013-11-16 16:59:16"
                },
                {
                    "start": "2013-11-16 17:00:03",
                    "end": "2013-11-16 17:01:00"
                },
                {
                    "start": "2013-11-16 17:02:10",
                    "end": "2013-11-16 17:04:16"
                },
                {
                    "start": "2013-11-16 17:06:23",
                    "end": "2013-11-16 17:07:11"
                },
                {
                    "start": "2013-11-16 17:11:48",
                    "end": "2013-11-16 17:15:05"
                },
                {
                    "start": "2013-11-16 17:34:08",
                    "end": "2013-11-16 17:38:17"
                },
                {
                    "start": "2013-11-16 17:41:52",
                    "end": "2013-11-16 17:43:17"
                },
                {
                    "start": "2013-11-16 17:43:43",
                    "end": "2013-11-16 17:44:44"
                },
                {
                    "start": "2013-11-16 17:47:12",
                    "end": "2013-11-16 17:48:15"
                },
                {
                    "start": "2013-11-16 17:48:39",
                    "end": "2013-11-16 17:49:06"
                },
                {
                    "start": "2013-11-16 17:49:43",
                    "end": "2013-11-16 17:49:47"
                },
                {
                    "start": "2013-11-16 17:55:28",
                    "end": "2013-11-16 17:55:32"
                },
                {
                    "start": "2013-11-16 18:25:20",
                    "end": "2013-11-16 18:25:51"
                },
                {
                    "start": "2013-11-16 18:27:58",
                    "end": "2013-11-16 18:32:16"
                },
                {
                    "start": "2013-11-16 18:34:17",
                    "end": "2013-11-16 18:34:46"
                },
                {
                    "start": "2013-11-16 18:42:04",
                    "end": "2013-11-16 18:43:21"
                },
                {
                    "start": "2013-11-16 18:45:19",
                    "end": "2013-11-16 18:45:25"
                },
                {
                    "start": "2013-11-16 18:51:27",
                    "end": "2013-11-16 18:51:59"
                },
                {
                    "start": "2013-11-16 18:52:39",
                    "end": "2013-11-16 18:54:46"
                },
                {
                    "start": "2013-11-16 19:28:33",
                    "end": "2013-11-16 19:28:40"
                },
                {
                    "start": "2013-11-16 19:28:46",
                    "end": "2013-11-16 19:28:49"
                },
                {
                    "start": "2013-11-16 19:28:58",
                    "end": "2013-11-16 19:29:06"
                },
                {
                    "start": "2013-11-16 19:29:13",
                    "end": "2013-11-16 19:29:22"
                },
                {
                    "start": "2013-11-16 19:30:09",
                    "end": "2013-11-16 19:30:25"
                },
                {
                    "start": "2013-11-16 19:30:40",
                    "end": "2013-11-16 19:31:33"
                },
                {
                    "start": "2013-11-16 19:31:47",
                    "end": "2013-11-16 19:36:33"
                },
                {
                    "start": "2013-11-16 19:36:37",
                    "end": "2013-11-16 19:36:48"
                },
                {
                    "start": "2013-11-16 19:38:08",
                    "end": "2013-11-16 19:41:17"
                },
                {
                    "start": "2013-11-16 19:41:25",
                    "end": "2013-11-16 19:42:01"
                },
                {
                    "start": "2013-11-16 19:44:17",
                    "end": "2013-11-16 19:44:52"
                },
                {
                    "start": "2013-11-16 19:46:37",
                    "end": "2013-11-16 19:46:42"
                },
                {
                    "start": "2013-11-16 19:53:22",
                    "end": "2013-11-16 19:55:54"
                },
                {
                    "start": "2013-11-16 20:12:57",
                    "end": "2013-11-16 20:13:17"
                },
                {
                    "start": "2013-11-16 20:33:49",
                    "end": "2013-11-16 20:33:57"
                },
                {
                    "start": "2013-11-16 20:34:08",
                    "end": "2013-11-16 20:34:17"
                },
                {
                    "start": "2013-11-16 20:34:53",
                    "end": "2013-11-16 20:34:56"
                },
                {
                    "start": "2013-11-16 20:39:17",
                    "end": "2013-11-16 20:39:20"
                },
                {
                    "start": "2013-11-16 20:39:55",
                    "end": "2013-11-16 20:40:46"
                },
                {
                    "start": "2013-11-16 20:40:53",
                    "end": "2013-11-16 20:40:57"
                },
                {
                    "start": "2013-11-16 20:45:12",
                    "end": "2013-11-16 20:50:23"
                },
                {
                    "start": "2013-11-16 20:51:11",
                    "end": "2013-11-16 20:51:49"
                },
                {
                    "start": "2013-11-16 20:52:04",
                    "end": "2013-11-16 21:17:56"
                },
                {
                    "start": "2013-11-16 21:18:41",
                    "end": "2013-11-16 21:19:22"
                },
                {
                    "start": "2013-11-16 21:20:42",
                    "end": "2013-11-16 21:22:12"
                },
                {
                    "start": "2013-11-16 21:23:58",
                    "end": "2013-11-16 21:24:28"
                },
                {
                    "start": "2013-11-16 21:29:08",
                    "end": "2013-11-16 21:29:25"
                },
                {
                    "start": "2013-11-16 21:50:07",
                    "end": "2013-11-16 21:50:55"
                },
                {
                    "start": "2013-11-16 21:51:32",
                    "end": "2013-11-16 21:51:35"
                },
                {
                    "start": "2013-11-16 21:52:46",
                    "end": "2013-11-16 21:52:49"
                }
            ]
        },
        {
            "name": "bedroom",
            "transName": "bedroom",
            "locations": [
                {
                    "start": "2013-11-16 00:00:00",
                    "end": "2013-11-16 02:14:14"
                },
                {
                    "start": "2013-11-16 02:17:46",
                    "end": "2013-11-16 08:19:22"
                },
                {
                    "start": "2013-11-16 08:25:43",
                    "end": "2013-11-16 09:16:55"
                },
                {
                    "start": "2013-11-16 21:56:23",
                    "end": "2013-11-16 22:36:01"
                },
                {
                    "start": "2013-11-16 23:03:31",
                    "end": "2013-11-16 23:03:57"
                },
                {
                    "start": "2013-11-16 23:05:55",
                    "end": "2013-11-17 00:00:00"
                }
            ]
        },
        {
            "name": "spareroom",
            "transName": "spareroom",
            "locations": [
                {
                    "start": "2013-11-16 17:38:17",
                    "end": "2013-11-16 17:39:42"
                }
            ]
        },
        {
            "name": "outside",
            "transName": "outside",
            "locations": [
                {
                    "start": "2013-11-16 10:16:52",
                    "end": "2013-11-16 10:16:55"
                },
                {
                    "start": "2013-11-16 11:42:03",
                    "end": "2013-11-16 15:38:07"
                },
                {
                    "start": "2013-11-16 15:39:52",
                    "end": "2013-11-16 15:39:55"
                },
                {
                    "start": "2013-11-16 15:41:14",
                    "end": "2013-11-16 15:42:37"
                },
                {
                    "start": "2013-11-16 19:28:40",
                    "end": "2013-11-16 19:28:46"
                },
                {
                    "start": "2013-11-16 20:44:49",
                    "end": "2013-11-16 20:45:12"
                }
            ]
        }
    ]
}